jotquote/__init__.py
jotquote/api.py
jotquote/cli.py
jotquote/web.py
jotquote/static/favicon.ico
jotquote/templates/quote.html
jotquote/templates/quotes.txt
jotquote/templates/unavailable.html
jotquote-0.9.4.dist-info/LICENSE.txt
jotquote-0.9.4.dist-info/METADATA
jotquote-0.9.4.dist-info/WHEEL
jotquote-0.9.4.dist-info/entry_points.txt
jotquote-0.9.4.dist-info/top_level.txt
jotquote-0.9.4.dist-info/RECORD
