Metadata-Version: 2.1
Name: jotquote
Version: 0.9.4
Summary: A command-line interface for collecting and organizing quotes, and a quote of the day web server.
Home-page: UNKNOWN
Author: Jake Kugel
Author-email: jake_kugel@yahoo.com
License: MIT License
Keywords: quotes
Platform: UNKNOWN
Classifier: Development Status :: 4 - Beta
Classifier: Environment :: Console
Classifier: Environment :: Web Environment
Classifier: Operating System :: MacOS :: MacOS X
Classifier: Operating System :: Microsoft :: Windows
Classifier: Operating System :: POSIX
Classifier: Programming Language :: Python :: 2.7
Classifier: Programming Language :: Python :: 3.5
Classifier: Programming Language :: Python :: 3.6
Classifier: Programming Language :: Python :: 3.7
Classifier: Programming Language :: Python :: 3.8
Classifier: License :: OSI Approved :: MIT License
Requires-Python: >=2.7, !=3.0.*, !=3.1.*, !=3.2.*, !=3.3.*, !=3.4.*, <4
Requires-Dist: flask (>=0.10.1)
Requires-Dist: configparser (>=3.5.0)
Requires-Dist: future (>=0.16.0)
